drf_api_action/__init__.py
drf_api_action/exceptions.py
drf_api_action/mixins.py
drf_api_action/plugin.py
drf_api_action/utils.py
drf_api_action-1.2.2.dist-info/METADATA
drf_api_action-1.2.2.dist-info/WHEEL
drf_api_action-1.2.2.dist-info/entry_points.txt
drf_api_action-1.2.2.dist-info/RECORD
