Metadata-Version: 2.1
Name: drf_api_action
Version: 1.2.2
Summary: drf-api-action elevates DRF testing by simplifying REST endpoint testing to a seamless, function-like experience.
Home-page: https://github.com/Ori-Roza/drf-api-action
License: MIT
Keywords: pytest,mocks,testing,fixtures,tests,django
Author: Ori Roza
Author-email: ori75660@gmail.com
Requires-Python: >=3.7,<4.0
Classifier: Development Status :: 5 - Production/Stable
Classifier: Framework :: Pytest
Classifier: Intended Audience :: Developers
Classifier: License :: OSI Approved :: MIT License
Classifier: Operating System :: OS Independent
Classifier: Programming Language :: Python
Classifier: Programming Language :: Python :: 3
Classifier: Programming Language :: Python :: 3.7
Classifier: Programming Language :: Python :: 3.8
Classifier: Programming Language :: Python :: 3.9
Classifier: Programming Language :: Python :: 3.10
Classifier: Programming Language :: Python :: 3.11
Classifier: Programming Language :: Python :: 3.12
Classifier: Topic :: Software Development :: Testing
Requires-Dist: Django (>=4.2.8)
Requires-Dist: djangorestframework (>=3.14.0)
Requires-Dist: importlib_metadata (>=4.5.0,<5.0.0) ; python_version < "3.8"
Requires-Dist: pytest-cov (==4.1.0)
Requires-Dist: pytest-django (>=4.5.2)
Project-URL: Repository, https://github.com/Ori-Roza/drf-api-action
